xiaohongshu_mcp.py
redbook_search_comment-0.1.0.dist-info/METADATA
redbook_search_comment-0.1.0.dist-info/WHEEL
redbook_search_comment-0.1.0.dist-info/top_level.txt
redbook_search_comment-0.1.0.dist-info/RECORD
