Metadata-Version: 2.4
Name: redbook-search-comment
Version: 0.1.0
Summary: Custom MCP service for Redbook comment search
Author-email: tt <18662746901@163.com>
License: MIT
Requires-Python: >=3.10
Requires-Dist: playwright>=1.40.0
Requires-Dist: pytest-playwright>=0.4.0
Requires-Dist: pandas>=2.1.1
Requires-Dist: numpy>=1.26.4
Requires-Dist: asyncio==3.4.3
Requires-Dist: mcp[cli]
Requires-Dist: python-dotenv==1.0.0
Requires-Dist: requests==2.31.0
Requires-Dist: schedule==1.2.0
Requires-Dist: tqdm==4.66.1
Requires-Dist: fastapi>=0.95.1
Requires-Dist: uvicorn>=0.22.0
